{
  "rules": [
    {
      "id": "R-1-0001",
      "section_id": "S-1",
      "tags": [
        "eligibility"
      ],
      "text": "Projects aggregate manure from multiple farms and install a central methane capture system where the baseline lacks methane recovery."
    },
    {
      "id": "R-1-0002",
      "section_id": "S-2",
      "tags": [
        "calc",
        "baseline",
        "additionality"
      ],
      "text": "Baseline is the highest-IRR alternative without methane recovery determined through the methodology's IRR/NPV screening steps."
    },
    {
      "id": "R-1-0003",
      "section_id": "S-2",
      "tags": [
        "reporting"
      ],
      "text": "Barrier documentation and CER transfer declarations demonstrate participation and prevent double counting."
    },
    {
      "id": "R-1-0004",
      "section_id": "S-3",
      "tags": [
        "parameter",
        "project_design"
      ],
      "text": "Project boundaries cover collection through final sludge treatment with leak-proof infrastructure and consistent fertilizer use."
    },
    {
      "id": "R-1-0005",
      "section_id": "S-3",
      "tags": [
        "equation",
        "calc"
      ],
      "text": "Emission reductions equal avoided manure methane minus project emissions following the referenced AM tools."
    },
    {
      "id": "R-1-0006",
      "section_id": "S-4",
      "tags": [
        "leakage"
      ],
      "text": "Deduct leakage from pipelines, auxiliary fuel, and offsite residue handling using monitored data or LFAD defaults."
    },
    {
      "id": "R-1-0007",
      "section_id": "S-5",
      "tags": [
        "monitoring"
      ],
      "text": "Monitor biogas, methane fraction, and energy consumption continuously and report at least monthly with QA/QC evidence."
    },
    {
      "id": "R-1-0008",
      "section_id": "S-5",
      "tags": [
        "reporting"
      ],
      "text": "Focus DOE inspections on high-emitting farms and reconcile methane balances annually, documenting leak investigations and fixes."
    }
  ]
}
