{
  "sections": [
    {
      "id": "S-0001",
      "title": "UNFCCC/CCNUCC",
      "anchor": "unfccc-ccnucc"
    },
    {
      "id": "S-0002",
      "title": "EB 39",
      "anchor": "eb-39"
    },
    {
      "id": "S-0003",
      "title": "TYPE III – OTHER PROJECT TYPES",
      "anchor": "type-iii-other-project-types"
    },
    {
      "id": "S-0004",
      "title": "In a two-year cropping sequence this corresponds to the previous six years. In a one-year cropping",
      "anchor": "in-a-two-year-cropping-sequence-this-corresponds-to-the-previous-six-years-in-a-one-year-cropping"
    },
    {
      "id": "S-0005",
      "title": "UNFCCC/CCNUCC",
      "anchor": "unfccc-ccnucc-2"
    },
    {
      "id": "S-0006",
      "title": "EB 39",
      "anchor": "eb-39-2"
    },
    {
      "id": "S-0007",
      "title": "kt CO2 equivalent annually.",
      "anchor": "kt-co2-equivalent-annually"
    },
    {
      "id": "S-0008",
      "title": "UNFCCC/CCNUCC",
      "anchor": "unfccc-ccnucc-3"
    },
    {
      "id": "S-0009",
      "title": "EB 39",
      "anchor": "eb-39-3"
    },
    {
      "id": "S-0010",
      "title": "1 to 3",
      "anchor": "1-to-3"
    },
    {
      "id": "S-0011",
      "title": "Fine",
      "anchor": "fine"
    },
    {
      "id": "S-0012",
      "title": "Cold temperate",
      "anchor": "cold-temperate"
    },
    {
      "id": "S-0013",
      "title": "Cold temperate",
      "anchor": "cold-temperate-2"
    },
    {
      "id": "S-0014",
      "title": "Poorly drained",
      "anchor": "poorly-drained"
    },
    {
      "id": "S-0015",
      "title": "Sandy, loamy sandy, sandy",
      "anchor": "sandy-loamy-sandy-sandy"
    },
    {
      "id": "S-0016",
      "title": "Sandy clay loam, clay",
      "anchor": "sandy-clay-loam-clay"
    },
    {
      "id": "S-0017",
      "title": "Sandy clay, silty clay, clay",
      "anchor": "sandy-clay-silty-clay-clay"
    },
    {
      "id": "S-0018",
      "title": "Stehfest, E. (2005): Modelling of global crop production and resulting N2O emissions. Dissertation.",
      "anchor": "stehfest-e-2005-modelling-of-global-crop-production-and-resulting-n2o-emissions-dissertation"
    },
    {
      "id": "S-0019",
      "title": "IPCC (2006): IPCC Good Practice Guidance and Uncertainty Management in National GHG Inventories.",
      "anchor": "ipcc-2006-ipcc-good-practice-guidance-and-uncertainty-management-in-national-ghg-inventories"
    },
    {
      "id": "S-0020",
      "title": "UNFCCC/CCNUCC",
      "anchor": "unfccc-ccnucc-4"
    },
    {
      "id": "S-0021",
      "title": "EB 39",
      "anchor": "eb-39-4"
    },
    {
      "id": "S-0022",
      "title": "In the absence of reliable project specific data, a conservative value from referenced scientific literature may",
      "anchor": "in-the-absence-of-reliable-project-specific-data-a-conservative-value-from-referenced-scientific-literature-may"
    },
    {
      "id": "S-0023",
      "title": "UNFCCC/CCNUCC",
      "anchor": "unfccc-ccnucc-5"
    },
    {
      "id": "S-0024",
      "title": "EB 39",
      "anchor": "eb-39-5"
    },
    {
      "id": "S-0025",
      "title": "UNFCCC/CCNUCC",
      "anchor": "unfccc-ccnucc-6"
    },
    {
      "id": "S-0026",
      "title": "EB 39",
      "anchor": "eb-39-6"
    },
    {
      "id": "S-0027",
      "title": "Monitoring shall include all farmers i that take part in the project activity. The following",
      "anchor": "monitoring-shall-include-all-farmers-i-that-take-part-in-the-project-activity-the-following"
    },
    {
      "id": "S-0028",
      "title": "UNFCCC/CCNUCC",
      "anchor": "unfccc-ccnucc-7"
    },
    {
      "id": "S-0029",
      "title": "EB 39",
      "anchor": "eb-39-7"
    },
    {
      "id": "S-0030",
      "title": "While visiting the fields the independent third party will also check the farmers’ records on",
      "anchor": "while-visiting-the-fields-the-independent-third-party-will-also-check-the-farmers-records-on"
    },
    {
      "id": "S-0031",
      "title": "UNFCCC/CCNUCC",
      "anchor": "unfccc-ccnucc-8"
    },
    {
      "id": "S-0032",
      "title": "EB 39",
      "anchor": "eb-39-8"
    },
    {
      "id": "S-0033",
      "title": "UNFCCC/CCNUCC",
      "anchor": "unfccc-ccnucc-9"
    },
    {
      "id": "S-0034",
      "title": "EB 39",
      "anchor": "eb-39-9"
    },
    {
      "id": "S-0035",
      "title": "FIELD VISIT MONITORING PROTOCOL FOR UREA AND INOCULANT APPLICATION",
      "anchor": "field-visit-monitoring-protocol-for-urea-and-inoculant-application"
    },
    {
      "id": "S-0036",
      "title": "“Sampling”, by Dr. H. Reetz, http://www.rainbowplantfood.com/agronomics/efu/sampling.pdf accessed on",
      "anchor": "sampling-by-dr-h-reetz-http-www-rainbowplantfood-com-agronomics-efu-sampling-pdf-accessed-on"
    },
    {
      "id": "S-0037",
      "title": "UNFCCC/CCNUCC",
      "anchor": "unfccc-ccnucc-10"
    },
    {
      "id": "S-0038",
      "title": "EB 39",
      "anchor": "eb-39-10"
    },
    {
      "id": "S-0039",
      "title": "May 2008",
      "anchor": "may-2008"
    }
  ]
}
