{
  "rules": [
    {
      "id": "R-1-0001",
      "section_id": "S-1",
      "tags": [
        "eligibility"
      ],
      "text": "Project restores degraded forest lands and meets additionality tests per Tool 01."
    },
    {
      "id": "R-1-0002",
      "section_id": "S-2",
      "tags": [
        "calc",
        "baseline"
      ],
      "text": "Baseline net GHG removals derived from historical land-use data per Tool 02 guidance."
    },
    {
      "id": "R-1-0003",
      "section_id": "S-3",
      "tags": [
        "calc",
        "emissions"
      ],
      "text": "Project emissions include fossil fuel use, biomass burning, and fertilizer application as per Tool 08."
    },
    {
      "id": "R-1-0004",
      "section_id": "S-4",
      "tags": [
        "leakage"
      ],
      "text": "Leakage from activity shifting and market effects addressed using Tool 14 default factors."
    },
    {
      "id": "R-1-0005",
      "section_id": "S-5",
      "tags": [
        "monitoring"
      ],
      "text": "Non-permanence buffer determined via Tool 15 risk analysis and recorded in registry accounts."
    },
    {
      "id": "R-1-0006",
      "section_id": "S-5",
      "tags": [
        "monitoring"
      ],
      "text": "Permanent sample plots re-measured at least every five years per Tool 16 QA/QC guidance."
    },
    {
      "id": "R-1-0007",
      "section_id": "S-5",
      "tags": [
        "uncertainty"
      ],
      "text": "Sampling uncertainty kept below 10% at 90% confidence or conservatively adjusted using Tool 12."
    },
    {
      "id": "R-1-0008",
      "section_id": "S-5",
      "tags": [
        "reporting"
      ],
      "text": "Monitoring reports compile geospatial data, emissions sources, and buffer transactions with full audit trail."
    }
  ]
}
